README.md
setup.py
MRA.egg-info/PKG-INFO
MRA.egg-info/SOURCES.txt
MRA.egg-info/dependency_links.txt
MRA.egg-info/entry_points.txt
MRA.egg-info/top_level.txt
mra/__init__.py
mra/__main__.py
mra/durable_state.py
mra/dynamic_module.py
mra/http_pool.py
mra/management.py
mra/resource_pool.py
mra/settings.py
mra/task.py
mra.egg-info/PKG-INFO
mra.egg-info/SOURCES.txt
mra.egg-info/dependency_links.txt
mra.egg-info/entry_points.txt
mra.egg-info/pbr.json
mra.egg-info/requires.txt
mra.egg-info/top_level.txt
mra/actions/__init__.py
mra/actions/action.py
mra/actions/simple_actions.py
mra/actions/task_generator.py
mra/display/__init__.py
mra/display/display_layer.py
mra/display/meta.py
mra/helpers/__init__.py
mra/helpers/logger.py
mra/helpers/parser.py
mra/helpers/util.py